civicpy/__init__.py
civicpy/__version__.py
civicpy/civic.py
civicpy/cli.py
civicpy/graphql_payloads.py
civicpy/utils.py
civicpy/exports/__init__.py
civicpy/exports/civic_gks_record.py
civicpy/exports/civic_gks_writer.py
civicpy/exports/civic_vcf_record.py
civicpy/exports/civic_vcf_writer.py
civicpy-5.1.1.dist-info/licenses/LICENSE
civicpy-5.1.1.dist-info/METADATA
civicpy-5.1.1.dist-info/WHEEL
civicpy-5.1.1.dist-info/entry_points.txt
civicpy-5.1.1.dist-info/top_level.txt
civicpy-5.1.1.dist-info/RECORD
